Metadata-Version: 1.0
Name: mypkgtest
Version: 0.1
Summary: The funniest joke in the world
Home-page: http://github.com/sean-bai/mypkgtest
Author: sean-bai
Author-email: zhihengbai@gmail.com
License: MIT
Platform: UNKNOWN
